[{
        "categoria": "Anatomia",
        "pregunta": "¿Que es el Corazon?",
        "respuesta": "Musculo",
        "incorrecta1": "Pie",
        "incorrecta2": "Organo",
        "incorrecta3": "Bicibleta",
        "imagen": "https://lh3.googleusercontent.com/proxy/dF5-UNv8HSwM4scRVNu6HXt5anx87-LYhmjy_2Rhp1VY_iBugBbcbI0_4GaInZN7jIp2mJhGvv7F8AvTWjniHWrI5QwldOphX5T7bq2f5le7dacWGE2EFBXsxsBfeL8oAtQtRldYlfmDGg",
        "objectFit": "cover"
    },
    {
        "categoria": "Anatomia",
        "pregunta": "¿Que es?",
        "respuesta": "Tibia",
        "incorrecta1": "creano",
        "incorrecta2": "Un Coreano en chancleta",
        "incorrecta3": "dedo",
        "imagen": "https://cdn.hum3d.com/wp-content/uploads/Anatomy/024_Human_Tibia_Fibula/Human_Tibia_Fibula_1000_0001.jpg",
        "objectFit": "contain"
    },
    {
        "categoria": "Anatomia",
        "pregunta": "Serie americana donde los personajes son amarillos",
        "respuesta": "Los simpsos",
        "incorrecta1": "Padre de familia",
        "incorrecta2": "South park",
        "incorrecta3": "La casa de los dibujos"
    },
    {
        "categoria": "Fundamentos",
        "pregunta": "Como se distingue una ulcera de grado 1?",
        "respuesta": "Se puede notar la piel rojisa",
        "incorrecta1": "Se le cae el pelo",
        "incorrecta2": "Dolar a $200",
        "incorrecta3": "Tiene tos"
    }
]